jwxml/VERSION
jwxml/__init__.py
jwxml/constants.py
jwxml/mirrors.py
jwxml/siaf.py
jwxml/utils.py
jwxml/data/PRDDEVSOC-D-012/FGS_SIAF.xml
jwxml/data/PRDDEVSOC-D-012/MIRI_SIAF.xml
jwxml/data/PRDDEVSOC-D-012/NIRCam_SIAF.xml
jwxml/data/PRDDEVSOC-D-012/NIRISS_SIAF.xml
jwxml/data/PRDDEVSOC-D-012/NIRSpec_SIAF.xml
jwxml/data/PRDOPSSOC-E-002/FGS_SIAF.xml
jwxml/data/PRDOPSSOC-E-002/MIRI_SIAF.xml
jwxml/data/PRDOPSSOC-E-002/NIRCam_SIAF.xml
jwxml/data/PRDOPSSOC-E-002/NIRISS_SIAF.xml
jwxml/data/PRDOPSSOC-E-002/NIRSpec_SIAF.xml
jwxml/data/PRDOPSSOC-F-008/FGS_SIAF.xml
jwxml/data/PRDOPSSOC-F-008/MIRI_SIAF.xml
jwxml/data/PRDOPSSOC-F-008/NIRCam_SIAF.xml
jwxml/data/PRDOPSSOC-F-008/NIRISS_SIAF.xml
jwxml/data/PRDOPSSOC-F-008/NIRSpec_SIAF.xml
jwxml/tests/__init__.py
jwxml/tests/test_siaf.py
jwxml-0.3.0.dist-info/DESCRIPTION.rst
jwxml-0.3.0.dist-info/METADATA
jwxml-0.3.0.dist-info/RECORD
jwxml-0.3.0.dist-info/WHEEL
jwxml-0.3.0.dist-info/metadata.json
jwxml-0.3.0.dist-info/top_level.txt
