Metadata-Version: 2.0
Name: jwxml
Version: 0.3.0
Summary: Parse and manipulate XML files, mostly JWST optics and wavefront sensing related.
Home-page: https://github.com/mperrin/jwxml
Author: Marshall Perrin, Joseph Long
Author-email: help@stsci.edu
License: BSD
Keywords: jwst xml siaf
Platform: UNKNOWN
Classifier: Development Status :: 3 - Alpha
Classifier: Intended Audience :: Developers
Classifier: Topic :: Scientific/Engineering :: Astronomy
Classifier: License :: OSI Approved :: BSD License
Classifier: Operating System :: OS Independent
Classifier: Programming Language :: Python :: 2
Classifier: Programming Language :: Python :: 2.7
Classifier: Programming Language :: Python :: 3
Classifier: Programming Language :: Python :: 3.5
Requires-Dist: matplotlib (>=1.4.3)
Requires-Dist: numpy (>=1.9)
Provides-Extra: dev
Requires-Dist: check-manifest (>=0.34); extra == 'dev'
Requires-Dist: lxml (>=3.6.4); extra == 'dev'
Requires-Dist: pytest (>=3.0.2); extra == 'dev'
